{
  "vp_card": {
    "shape": "b",
    "direction": "SHORT",
    "poc": 59980,
    "vah": 59980,
    "val": 59949,
    "hvn_range": "59961-59980",
    "touch_count_val": 0,
    "touch_count_vah": 0,
    "probability_tier": "BASELINE",
    "acceptance_rejection_state": "ACCEPTANCE",
    "rejection_direction": null,
    "consecutive_closes_outside_va": 0,
    "confirmation_status": "PENDING",
    "active_pattern": "POC_MAGNET",
    "strategy_bias": "FADE",
    "amt_lockout": true,
    "amt_verdict": "NO_TRADE",
    "adx": 0,
    "entry_level": 59982,
    "t1": 59980,
    "t2": 59949,
    "stop_loss": 59986,
    "invalidation": 59992,
    "rr_t1": 0.48,
    "rr_t2": 7.86,
    "size_recommendation": "SKIP",
    "trade_setups": [
      {
        "direction": "SHORT",
        "entry": 59982,
        "t1": 59980,
        "t2": 59949,
        "stop_loss": 59986,
        "invalidation": 59992,
        "rr_t1": 0.48,
        "rr_t2": 7.86
      }
    ],
    "btc_price": 59978,
    "session": "LONDON",
    "last_updated": "2026-06-28T06:48:03.576575+00:00"
  },
  "chart_data": {
    "bin_size": 1,
    "max_volume": 10.08,
    "bins": [
      {
        "price": 59990,
        "volume": 1.81,
        "type": "normal"
      },
      {
        "price": 59988,
        "volume": 0.34,
        "type": "lvn"
      },
      {
        "price": 59987,
        "volume": 0.01,
        "type": "lvn"
      },
      {
        "price": 59986,
        "volume": 0.13,
        "type": "lvn"
      },
      {
        "price": 59985,
        "volume": 2.83,
        "type": "normal"
      },
      {
        "price": 59984,
        "volume": 2.32,
        "type": "normal"
      },
      {
        "price": 59983,
        "volume": 0.0,
        "type": "lvn"
      },
      {
        "price": 59982,
        "volume": 0.1,
        "type": "vah"
      },
      {
        "price": 59981,
        "volume": 0.01,
        "type": "poc"
      },
      {
        "price": 59980,
        "volume": 10.08,
        "type": "poc"
      },
      {
        "price": 59979,
        "volume": 0.1,
        "type": "poc"
      },
      {
        "price": 59978,
        "volume": 0.21,
        "type": "vah"
      },
      {
        "price": 59976,
        "volume": 0.21,
        "type": "lvn"
      },
      {
        "price": 59974,
        "volume": 0.06,
        "type": "lvn"
      },
      {
        "price": 59973,
        "volume": 0.02,
        "type": "lvn"
      },
      {
        "price": 59972,
        "volume": 0.09,
        "type": "lvn"
      },
      {
        "price": 59970,
        "volume": 2.67,
        "type": "normal"
      },
      {
        "price": 59969,
        "volume": 0.29,
        "type": "lvn"
      },
      {
        "price": 59968,
        "volume": 0.04,
        "type": "lvn"
      },
      {
        "price": 59967,
        "volume": 0.28,
        "type": "lvn"
      },
      {
        "price": 59966,
        "volume": 0.14,
        "type": "lvn"
      },
      {
        "price": 59965,
        "volume": 0.02,
        "type": "lvn"
      },
      {
        "price": 59964,
        "volume": 1.18,
        "type": "normal"
      },
      {
        "price": 59963,
        "volume": 0.69,
        "type": "lvn"
      },
      {
        "price": 59962,
        "volume": 1.16,
        "type": "normal"
      },
      {
        "price": 59961,
        "volume": 1.71,
        "type": "normal"
      },
      {
        "price": 59960,
        "volume": 0.76,
        "type": "lvn"
      },
      {
        "price": 59959,
        "volume": 5.35,
        "type": "hvn"
      },
      {
        "price": 59958,
        "volume": 1.95,
        "type": "normal"
      },
      {
        "price": 59957,
        "volume": 1.69,
        "type": "normal"
      },
      {
        "price": 59956,
        "volume": 0.93,
        "type": "lvn"
      },
      {
        "price": 59955,
        "volume": 1.21,
        "type": "normal"
      },
      {
        "price": 59954,
        "volume": 1.65,
        "type": "normal"
      },
      {
        "price": 59953,
        "volume": 0.26,
        "type": "lvn"
      },
      {
        "price": 59952,
        "volume": 0.24,
        "type": "lvn"
      },
      {
        "price": 59951,
        "volume": 0.22,
        "type": "val"
      },
      {
        "price": 59950,
        "volume": 0.79,
        "type": "val"
      },
      {
        "price": 59949,
        "volume": 1.76,
        "type": "val"
      },
      {
        "price": 59948,
        "volume": 0.41,
        "type": "val"
      },
      {
        "price": 59947,
        "volume": 0.4,
        "type": "val"
      },
      {
        "price": 59946,
        "volume": 0.04,
        "type": "lvn"
      },
      {
        "price": 59945,
        "volume": 0.05,
        "type": "lvn"
      },
      {
        "price": 59944,
        "volume": 0.31,
        "type": "lvn"
      },
      {
        "price": 59943,
        "volume": 0.08,
        "type": "lvn"
      },
      {
        "price": 59942,
        "volume": 0.15,
        "type": "lvn"
      },
      {
        "price": 59941,
        "volume": 0.05,
        "type": "lvn"
      },
      {
        "price": 59940,
        "volume": 0.05,
        "type": "lvn"
      },
      {
        "price": 59939,
        "volume": 0.11,
        "type": "lvn"
      },
      {
        "price": 59938,
        "volume": 0.12,
        "type": "lvn"
      },
      {
        "price": 59937,
        "volume": 0.46,
        "type": "lvn"
      },
      {
        "price": 59936,
        "volume": 0.02,
        "type": "lvn"
      },
      {
        "price": 59935,
        "volume": 0.01,
        "type": "lvn"
      },
      {
        "price": 59934,
        "volume": 0.02,
        "type": "lvn"
      },
      {
        "price": 59933,
        "volume": 0.0,
        "type": "lvn"
      },
      {
        "price": 59932,
        "volume": 0.02,
        "type": "lvn"
      },
      {
        "price": 59930,
        "volume": 0.02,
        "type": "lvn"
      },
      {
        "price": 59929,
        "volume": 0.02,
        "type": "lvn"
      },
      {
        "price": 59928,
        "volume": 0.01,
        "type": "lvn"
      },
      {
        "price": 59926,
        "volume": 0.01,
        "type": "lvn"
      },
      {
        "price": 59925,
        "volume": 4.76,
        "type": "normal"
      }
    ]
  }
}